{
  "indexes": [
    {
      "collectionGroup": "Registro_Animal",
      "queryScope": "COLLECTION_GROUP",
      "fields": [
        {
          "fieldPath": "ID_Produc",
          "order": "ASCENDING"
        },
        {
          "fieldPath": "ID",
          "order": "DESCENDING"
        }
      ]
    }
  ],
  "fieldOverrides": [
    {
      "collectionGroup": "Registro_Animal",
      "fieldPath": "Tipo",
      "indexes": [
        {
          "order": "ASCENDING",
          "queryScope": "COLLECTION_GROUP"
        }
      ]
    },
    {
      "collectionGroup": "Registro_Animal",
      "fieldPath": "Estado_Animal",
      "indexes": [
        {
          "order": "ASCENDING",
          "queryScope": "COLLECTION_GROUP"
        }
      ]
    },
    {
      "collectionGroup": "Vacunas",
      "fieldPath": "ID_Produc",
      "indexes": [
        {
          "order": "ASCENDING",
          "queryScope": "COLLECTION_GROUP"
        }
      ]
    },
    {
      "collectionGroup": "Vacunas",
      "fieldPath": "ID_Vacuna",
      "indexes": [
        {
          "order": "ASCENDING",
          "queryScope": "COLLECTION_GROUP"
        }
      ]
    },
    {
      "collectionGroup": "Vacunas",
      "fieldPath": "Tipo_Vacuna",
      "indexes": [
        {
          "order": "ASCENDING",
          "queryScope": "COLLECTION_GROUP"
        }
      ]
    }
  ]
}